{
    "id": "c738e36b-42db-48e7-8131-1a44dedc6136",
    "player1": "Marek",
    "player2": "Władek",
    "date": "2025-04-26 10:48:56",
    "sets_to_win": 2,
    "advantage_rule": true,
    "serving_player": 2,
    "current_set": 1,
    "is_tiebreak": false,
    "winner": 0,
    "score": {
        "player1": {
            "sets": [
                0,
                0,
                0
            ],
            "games": 3,
            "points": "30",
            "tiebreak_points": 0
        },
        "player2": {
            "sets": [
                0,
                0,
                0
            ],
            "games": 0,
            "points": "30",
            "tiebreak_points": 0
        }
    },
    "time": {
        "start": "2025-04-26 10:48:56",
        "end": "",
        "duration": 353.402942,
        "sets": [
            {
                "start": "2025-04-26 10:48:56",
                "end": "",
                "duration": 0
            }
        ],
        "current_game_start": "2025-04-26 10:54:41"
    },
    "history": [
        {
            "action": "match_created",
            "timestamp": "10:48:56"
        },
        {
            "timestamp": "10:49:36",
            "action": "add_point",
            "player": 1,
            "state_before": {
                "player1_points": "0",
                "player2_points": "0",
                "player1_games": 0,
                "player2_games": 0,
                "current_set": 1,
                "is_tiebreak": false
            }
        },
        {
            "timestamp": "10:49:39",
            "action": "remove_point",
            "player": 1,
            "state_before": {
                "player1_points": "15",
                "player2_points": "0",
                "player1_games": 0,
                "player2_games": 0,
                "current_set": 1,
                "is_tiebreak": false
            }
        },
        {
            "timestamp": "10:54:00",
            "action": "add_point",
            "player": 1,
            "state_before": {
                "player1_points": "0",
                "player2_points": "0",
                "player1_games": 0,
                "player2_games": 0,
                "current_set": 1,
                "is_tiebreak": false
            }
        },
        {
            "timestamp": "10:54:20",
            "action": "add_point",
            "player": 1,
            "state_before": {
                "player1_points": "15",
                "player2_points": "0",
                "player1_games": 0,
                "player2_games": 0,
                "current_set": 1,
                "is_tiebreak": false
            }
        },
        {
            "timestamp": "10:54:28",
            "action": "add_game",
            "player": 1,
            "state_before": {
                "player1_points": "30",
                "player2_points": "0",
                "player1_games": 0,
                "player2_games": 0,
                "current_set": 1,
                "is_tiebreak": false
            }
        },
        {
            "timestamp": "10:54:28",
            "action": "game_completed",
            "game_info": {
                "start": "2025-04-26 10:48:56",
                "end": "2025-04-26 10:54:28",
                "duration": 332.500298,
                "player1_points": "30",
                "player2_points": "0"
            }
        },
        {
            "timestamp": "10:54:28",
            "action": "game_completed",
            "game_info": {
                "start": "2025-04-26 10:54:28",
                "end": "2025-04-26 10:54:28",
                "duration": 0.500298,
                "player1_points": "30",
                "player2_points": "0"
            }
        },
        {
            "timestamp": "10:54:32",
            "action": "add_game",
            "player": 1,
            "state_before": {
                "player1_points": "30",
                "player2_points": "0",
                "player1_games": 1,
                "player2_games": 0,
                "current_set": 1,
                "is_tiebreak": false
            }
        },
        {
            "timestamp": "10:54:32",
            "action": "game_completed",
            "game_info": {
                "start": "2025-04-26 10:54:28",
                "end": "2025-04-26 10:54:32",
                "duration": 4.050617,
                "player1_points": "30",
                "player2_points": "0"
            }
        },
        {
            "timestamp": "10:54:32",
            "action": "game_completed",
            "game_info": {
                "start": "2025-04-26 10:54:32",
                "end": "2025-04-26 10:54:32",
                "duration": 0.050617,
                "player1_points": "30",
                "player2_points": "0"
            }
        },
        {
            "timestamp": "10:54:41",
            "action": "add_game",
            "player": 1,
            "state_before": {
                "player1_points": "30",
                "player2_points": "0",
                "player1_games": 2,
                "player2_games": 0,
                "current_set": 1,
                "is_tiebreak": false
            }
        },
        {
            "timestamp": "10:54:41",
            "action": "game_completed",
            "game_info": {
                "start": "2025-04-26 10:54:32",
                "end": "2025-04-26 10:54:41",
                "duration": 9.733634,
                "player1_points": "30",
                "player2_points": "0"
            }
        },
        {
            "timestamp": "10:54:41",
            "action": "game_completed",
            "game_info": {
                "start": "2025-04-26 10:54:41",
                "end": "2025-04-26 10:54:41",
                "duration": 0.734633,
                "player1_points": "30",
                "player2_points": "0"
            }
        },
        {
            "timestamp": "10:54:45",
            "action": "add_point",
            "player": 2,
            "state_before": {
                "player1_points": "30",
                "player2_points": "0",
                "player1_games": 3,
                "player2_games": 0,
                "current_set": 1,
                "is_tiebreak": false
            }
        },
        {
            "timestamp": "10:54:49",
            "action": "add_point",
            "player": 2,
            "state_before": {
                "player1_points": "30",
                "player2_points": "15",
                "player1_games": 3,
                "player2_games": 0,
                "current_set": 1,
                "is_tiebreak": false
            }
        }
    ],
    "appearance": {
        "theme": "roland-garros",
        "logo_url": "",
        "custom_colors": {
            "primary": "rgba(30, 144, 255, 0.7)",
            "secondary": "rgba(220, 20, 60, 0.7)",
            "background": "rgba(0, 0, 0, 0.8)"
        },
        "animations": true,
        "size": 100
    },
    "statistics": {
        "points_won": {
            "player1": 0,
            "player2": 0
        },
        "service_stats": {
            "player1": {
                "aces": 0,
                "double_faults": 0
            },
            "player2": {
                "aces": 0,
                "double_faults": 0
            }
        },
        "break_points": {
            "player1": {
                "faced": 0,
                "saved": 0,
                "converted": 0
            },
            "player2": {
                "faced": 0,
                "saved": 0,
                "converted": 0
            }
        },
        "game_durations": [
            332.500298,
            0.500298,
            4.050617,
            0.050617,
            9.733634,
            0.734633
        ],
        "longest_streak": {
            "player1": 0,
            "player2": 0,
            "current_streak": 0,
            "current_player": 0
        }
    }
}